pynanomodem/__init__.py
pynanomodem/common.py
pynanomodem/loader.py
pynanomodem/location.py
pynanomodem/message.py
pynanomodem/modem.py
pynanomodem/modems/__init__.py
pynanomodem/utils.py
pynanomodem-0.2.10.dist-info/LICENSE
pynanomodem-0.2.10.dist-info/METADATA
pynanomodem-0.2.10.dist-info/WHEEL
pynanomodem-0.2.10.dist-info/RECORD
