Metadata-Version: 2.3
Name: pynanomodem
Version: 0.2.10
Summary: A Python implementation for Viasat IoT Nano modems.
License: Apache2.0
Author: Your Name
Author-email: you@example.com
Requires-Python: >=3.10,<4.0
Classifier: License :: Other/Proprietary License
Classifier: Programming Language :: Python :: 3
Classifier: Programming Language :: Python :: 3.10
Classifier: Programming Language :: Python :: 3.11
Classifier: Programming Language :: Python :: 3.12
Classifier: Programming Language :: Python :: 3.13
Requires-Dist: pyatcommand (>=0.4.0,<0.5.0)
